L2dvExApi/ApiList.py
L2dvExApi/__init__.py
L2dvExApi/msg_list.py
L2dvExApi-1.2.dist-info/METADATA
L2dvExApi-1.2.dist-info/WHEEL
L2dvExApi-1.2.dist-info/top_level.txt
L2dvExApi-1.2.dist-info/RECORD
