Metadata-Version: 2.1
Name: L2dvExApi
Version: 1.2
Summary: API for Live2DViewerEX
Home-page: http://www.icedream.space
Author: Esdrin
Author-email: esdrin@icedream.space
License: MIT License
Keywords: live2d,api
Platform: any
Classifier: Development Status :: 4 - Beta
Classifier: Intended Audience :: Developers
Classifier: Topic :: Software Development :: Libraries
Classifier: Topic :: Software Development :: Libraries :: Python Modules
Classifier: Programming Language :: Python :: 3
Classifier: Programming Language :: Python :: 3.9
Requires-Dist: websocket-client
